victor_unbabel_test_cli/__init__.py
victor_unbabel_test_cli/main.py
victor_unbabel_test_cli/utils/delivery_time.py
victor_unbabel_test_cli/utils/interfaces.py
victor_unbabel_test_cli/utils/read_events.py
victor_unbabel_test_cli-0.1.4.dist-info/METADATA
victor_unbabel_test_cli-0.1.4.dist-info/WHEEL
victor_unbabel_test_cli-0.1.4.dist-info/entry_points.txt
victor_unbabel_test_cli-0.1.4.dist-info/RECORD
